{
  "name": "pinia-store-to-refs-dynamic-shape",
  "provenance": {
    "repository": "vuejs/pinia",
    "commit": "ee1a590d82425e511db62d108df58bd0b4258ebe",
    "path": "packages/pinia/src/storeToRefs.ts",
    "adaptation": "Distilled semantic pattern; not a verbatim upstream copy."
  },
  "modules": [
    {
      "id": "storeToRefs.ts",
      "file": "storeToRefs.ts",
      "language": "ts",
      "kind": "script"
    },
    {
      "id": "consumer.ts",
      "file": "consumer.ts",
      "language": "ts",
      "kind": "script"
    }
  ],
  "links": [
    {
      "from": "consumer.ts",
      "specifier": "./storeToRefs",
      "to": "storeToRefs.ts"
    }
  ],
  "expected": {
    "module": "consumer.ts",
    "binding": "payload",
    "kind": "conditional",
    "guards": ["ready"],
    "trace": false
  }
}
